## 함수형 자바

### 람다 문법
```java
// 1. 가장 기본적인 괄호 안에 명시적으로 타입이 지정된 매개변수와 바디 블록으로 구성
(String input) -> {
    return input != null;
} 

// 2. 타입추론을 통해 명시적 타입을 생략
input -> {
    return input != null;	
}

// 3. 명시적 타입이 지정된 매개변수 사용하고 중괄호 대신에 단일 표현식사용
(String input) -> input != null

// 4. 가장 간단한 방식, 타입추론 + 단일 표현식
input -> input != null
```

### 함수형 인터페이스

람다 표현식이 자바에서 일급 객체로 취급받기 위해서는 기존의 객체와 비슷한 표현 방식을 갖추어야 한다.

람다표현식은 특화된 인터페이스의 하위 타입으로 표현된다. 이렇게 특화된 인터페이스를 함수형 인터페이스라고 한다.

인터페이스를 함수형 인터페이스로 만드는 조건은 무엇일까? 바로, SAM(Single Abstract Method)이라는 특성을 만족해야한다.

이름에서 알 수 있듯이, SAM은 추상메서드를 한개를 가진 인터페이스의 특성을 의미한다
기본(default) 메서드나 정적(static) 메서드는 추상 메서드가 아니기 때문에, 여러 개 존재해도 괜찮다.

```java
// 필수 어노테이션은 아니다
@FunctionalInterface
public interface Predicate<T> {
	
    // 단일 추상 메서드
    boolean test(T t);
	
    default Predicate<T> and(Predicate<? super T> other) {
        // ...
    }
	
    default Predicate<T> negate() {
        // ...
    }
	
    default Predicate<T> or(Predicate<? super T> other) {
        // ...
    }
	
    static <T> Predicate<T> isEqual(Object targetRef) {
        // ...
    }
	
    static <T> Predicate<T> not(Predicate<? super T> target) {
        // ...
    }
}
```

단 하나의 추상 메서드를 가진 모든 인터페이스는 자동으로 함수형 인터페이스가 되며, 모두 람다로 표현할 수 있다.

### 람다와 외부 변수

람다는 캡처를 통해 람다가 정의된 생성 스코프 내의 상수와 변수를 획득할 수 있다.

```java
void capture() {
    var theAnswer = 42;
    Runnable printAnswer = () -> System.out.println("the answer is " + theAnswer);
	
    run(printAnswer);
}

void run(Runnable r) {
	r.run();
}

capture();
// the answer is 42
```

변수를 캡처하는 상황에서 JVM은 다양한 방식으로 코드를 변환할 수 있다. 이로 인해 추가적인 객체 할당이 발생하며, 이는 성능 및 가비지 컬렉터 시간에 영향을 줄 수 있다.

최고의 성능이 필요한 경우에는 불필요한 캡처 사용을 피하는것이 좋다.

> 람다 표현식이 외부 변수를 직접 참조하지 않고, 필요한 값을 매개변수로 전달받아 처리하도록 만드는게 좋다.

변수 캡처를 피해야 하는 또 다른 이유중 하나는 해당 변수가 Effectively final 이어야 한다는 필요성이 있기 때문이다.

### 익명 클래스는 무엇인가?

표면적으로 익명 클래스에 의해 구현된 함수형 인터페이스는 람다 표현식과 꽤 유사해 보이지만, 불필요한 부분이 있다는 점이 다르다.

```java
// 함수형 인터페이스
interface HelloWorld {
    String sayHello(String name);
}

// 익명 클래스
var helloWorld = new HelloWorld() {
    @Override
    public String sayHello(String name) {
        return "hello, " + name + "!";
    }
};

// 람다
HelloWorld helloWorldLambda = name -> "hello, " + name + "!";
```

람다 표현식이 함수형 인터페이스를 익명 클래스로 구현하는 것의 문법 설탕일 뿐이라는 뜻일까?

> 문법 설탕이란 프로그래밍 언어의 기능을 더 간결하고 편리하게 사용할 수 있도록 하는 문법적인 확장이다.

람다 표현식은 문법 설탕에 그치지 않고 실제로 그 이상의 기능을 갖는다. 실제 차이점은 가독성 외에도 생성된 바이트 코드와 런타임 처리 방식에 있다.

```java
// <익명 클래스>
// 새로운 익명 클래스 HelloWorldAnonymous$1의 인스턴스를 생성합니다.
0: new #7 
// 새로 생성된 객체의 참조를 스택에 복사합니다.
3: dup
// HelloWorldAnonymous$1 클래스의 생성자를 호출합니다.
4: invokespecial #9 
//  스택에서 객체 참조를 꺼내어 지역 변수 1에 저장합니다.
7: astore_1
// 메서드를 종료합니다.
8: return

// <람다>
// 명령어는 런타임에 필요한 메타데이터와 함께 람다 표현식을 인스턴스화합니다.
0: invokedynamic #7, 0 
// 생성된 람다 인스턴스를 스택에서 꺼내어 지역 변수 1에 저장합니다
5: astore_1
// 메서드를 종료합니다
6: return
```

람다 표현식이 문법 설탕 이상의 기능을 가지는 이유는 바로 이 invokedynamic 명령어를 통해 런타임에 동적으로 처리되기 때문입니다. 

이로 인해 불필요한 클래스 파일이 생성되지 않으며, 더 효율적으로 실행될 수 있습니다.

### 람다 생성

람다 표현식을 만들기 위해서는 단일 함수형 인터페이스를 표현해야한다.

```java
// 컴파일 실패
var isNull = (String value) -> value == null;

// 왼쪽에 타입이 정의 되어야 한다.
Predicate<String> isNull = value -> value == null;
```

기존의 정적 타입 시스템을 사용함으로써 람다는 자바에 완벽하게 적합하며 람다도 다른 타입이나 접근 방식과 마찬가지로 컴파일 시간 안정성을 제공받는다.

그러나 이러한 강력한 타입 시스템 때문에 자바의 람다 표현식은 일부 다른 언어의 람다 표현식보다 덜 유연하고 덜 동적이다.

두 람다가 동일한 SAM 시그니처를 공유한다고 해서 서로 교환할 수 있는 것은 아니다.

```java
interface LikePredicate<T> {
    boolean test(T value);
}

LikePredicate<String> isNull = value -> value == null;

Predicate<String> wontCompile = isNull;
// 에러:
// 호환되지않는 타입: LikePredicate<java.lang.String>은
// java.util.function.Predicate<java.lang.String>으로 변환될 수 없음
```

### 람다 호출

람다는 효과적인 함수형 인터페이스의 구체적인 구현체이다.

다른 함수형 언어들은 보통 람다를 더 동적으로 사용한다 그래서 자바에서의 람다 사용 패턴은 다른 언어들과 다소 다를 수 있다.

```javascript
let helloWorldJs = name -> "hello, " + name + "!"
let resultJs = helloWorldJs("Ben")
```

그러나 자바에서는 람다가 인터페이스의 다른 인스턴스와 마찬가지로 동작하기 때문에 람다의 SAM을 명시적으로 호출해줘야한다.

```java
Function<String, String> helloWorld = name -> "hello, " + name + "!";
var result = helloWorld.apply("Ben");
```

단일 추상 메서드를 호출하는 것은 다른 언어처럼 간결하지 않을 수 있지만 자바의 하위 호환성이 지속된다는 이점이 있다.

### 메서드 참조

새로운 연산자인 ::(이중 콜론)을 사용하여 기존의 메서드를 참조하는 간결한 문법 설탕으로, 기존의 메서드로부터 람다 표현식을 생성하는 대신 기존의 메서드를 참조하여 함수형 코드를 보다 간소화하는 역할을 한다.

람다 표현식을 대체하려는 내용과 참조하려는 메서드 종류에 따라 네가지 메서드 참조 방법을 사용할 수 있다.

#### 1. 정적 메서드 참조

클래스에 정의된 정적 메서드를 참조한다.

```java
// 람다
Function<Integer, String> asLambda = i -> Integer.toHexString(i);

// 정적 메서드 참조
Function<Integer, String> asRef = Integer::toHexString;
```

정적 메서드 참조는 일반적으로 `ClassName::staticMethodName`모양으로 사용된다.

#### 2. 바운드 비정적 메서드 참조

특정 객체 인스턴스에 바운드된 비정적 메서드를 참조합니다.

```java
var now = LocalDate.now();

// 기존 객체를 기반으로 한 람다
Predicate<LocalDate> isAfterNowAsLambda = date -> date.isAfter(now);

// 바운드 비정적 메서드 참조
Predicate<LocalDate> isAfterNowAsRef = now::isAfter; 
```

바운드 비정적 메서드 참조의 일반 구문은 다음과 같은 패턴으로 사용된다. `objectName::instanceMethodName`

#### 3. 언바운드 비정적 메서드 참조

이름에서 알 수 있듯이 특정 객체에 바운딩되지않고 타입의 인스턴스 메서드를 참조한다.

```java
// 람다
Fuction<String, String> toLowerCaseLambda = str -> str.toLowerCase();

// 언바운드 비정적 메서드 참조
Fuction<String, String> toLowerCaseRef = String::toLowerCase;
```

언바운드 비정적 메서드 참조의 일반적인 구문은 다음과 같은 패턴으로 사용된다. `ClassName::instanceMethodName`

#### 4. 생성자 참조

생성자 참조는 클래스의 생성자를 람다 표현식이나 메서드 참조와 함께 사용할 때 유용하다.

```java
// 람다
Function<String, Locale> newLocaleLambda = language -> new Locale(language);

// 생성자 참조
Fuction<String, Locale> newLocaleRef = Locale::new;
```

생성자 참조는 일반적으로 `ClassName::new`로 사용된다.



